harrison/__init__.py
harrison/package_version.py
harrison/profile.py
harrison/registered_timer.py
harrison/test_timer.py
harrison/timer.py
harrison/util/__init__.py
harrison/util/inspectlib.py
harrison/util/test_inspectlib.py
harrison-2.0.0.dist-info/LICENSE
harrison-2.0.0.dist-info/METADATA
harrison-2.0.0.dist-info/WHEEL
harrison-2.0.0.dist-info/top_level.txt
harrison-2.0.0.dist-info/RECORD
