Metadata-Version: 2.1
Name: harrison
Version: 2.0.0
Summary: Time a block of code
Home-page: https://github.com/metabolize/harrison
Author: Body Labs, Metabolize
Author-email: github@paulmelnikow.com
License: MIT
Platform: UNKNOWN
Classifier: Development Status :: 5 - Production/Stable
Classifier: Intended Audience :: Developers
Classifier: License :: OSI Approved :: BSD License
Classifier: Operating System :: OS Independent
Classifier: Programming Language :: Python :: 3
